Metadata-Version: 2.1
Name: TheAlgorithms-pkg
Version: 0.0.5
Summary: A sample package to demonstrate how the packaging work
Home-page: https://github.com/tivpheakkdey/TheAlgoritms_pkg
Author: Vireakpheakkdey Tiv
Author-email: vtiv@deakin.edu.au
License: UNKNOWN
Download-URL: https://github.com/tivpheakkdey/TheAlgoritms_pkg/archive/0.0.5.tar.gz
Platform: UNKNOWN
Classifier: Programming Language :: Python :: 3
Classifier: License :: OSI Approved :: MIT License
Classifier: Operating System :: OS Independent
Requires-Python: >=3.6
